cpuload/__init__.py
cpuload/cpuload.py
cpuload-1.0.0.dist-info/LICENSE.md
cpuload-1.0.0.dist-info/METADATA
cpuload-1.0.0.dist-info/entry_points.txt
cpuload-1.0.0.dist-info/WHEEL
cpuload-1.0.0.dist-info/RECORD
